distvis/__init__.py
distvis/aggregation_utils.py
distvis/categorical_utils.py
distvis/data_utils.py
distvis/distribution_utils.py
distvis/plots.py
distvis/special_types.py
distvis-0.2.4.dist-info/METADATA
distvis-0.2.4.dist-info/WHEEL
distvis-0.2.4.dist-info/RECORD
