Metadata-Version: 2.3
Name: distvis
Version: 0.2.4
Summary: Distribution of data visualizations for insights, feature engineering and debugging
Author: milo.iturra
Author-email: iturra.camilo@gmail.com
Requires-Python: >=3.10,<3.13
Classifier: Programming Language :: Python :: 3
Classifier: Programming Language :: Python :: 3.10
Classifier: Programming Language :: Python :: 3.11
Classifier: Programming Language :: Python :: 3.12
Requires-Dist: matplotlib (>=3.10.3,<4.0.0)
Requires-Dist: nbformat (>=5.9.0,<6.0.0)
Requires-Dist: numpy (>=1.24.4,<2.0.0)
Requires-Dist: pandas (>=2.0.3,<3.0.0)
Requires-Dist: plotly (>=5.16.1,<6.0.0)
Requires-Dist: scipy (>=1.10.1,<2.0.0)
Requires-Dist: statsmodels (>=0.14.0,<0.15.0)
